strela/__init__.py
strela/alert_generator.py
strela/alertstates/__init__.py
strela/alertstates/alertstate.py
strela/alertstates/alertstaterepository.py
strela/alertstates/doubledownalertstate.py
strela/alertstates/fluctulertstate.py
strela/config.py
strela/mailer.py
strela/my_runner.py
strela/symboltype.py
strela/templates.py
strela-0.4.dist-info/LICENSE
strela-0.4.dist-info/METADATA
strela-0.4.dist-info/WHEEL
strela-0.4.dist-info/RECORD
