Metadata-Version: 2.3
Name: strela
Version: 0.4
Summary: A python package for financial alerts
License: MIT
Keywords: python,finance,financial-analysis,financial,alerts,alerting,tessa
Author: ymyke
Requires-Python: >=3.11,<3.12
Classifier: License :: OSI Approved :: MIT License
Classifier: Programming Language :: Python :: 3
Classifier: Programming Language :: Python :: 3.11
Requires-Dist: keyring (>=23)
Requires-Dist: pandas (>=1.3.5)
Requires-Dist: python-slugify (>=5.0.0)
Requires-Dist: tessa (>=0,<1)
Requires-Dist: yagmail (>=0.15.280)
Project-URL: Documentation, https://ymyke.github.io/strela/strela.html
Project-URL: Homepage, https://github.com/ymyke/strela
Project-URL: Repository, https://github.com/ymyke/strela
